mkdocs_fedi_comments/FediverseLogo.svg
mkdocs_fedi_comments/__init__.py
mkdocs_fedi_comments/actor.py
mkdocs_fedi_comments/config.py
mkdocs_fedi_comments/file_maker.py
mkdocs_fedi_comments/link_maker.py
mkdocs_fedi_comments/test_actor.py
mkdocs_fedi_comments/test_link_maker.py
mkdocs_fedi_comments/version.py
mkdocs_fedi_comments/assets/dist/comments.js
mkdocs_fedi_comments/overrides/main.html
mkdocs_fedi_comments/overrides/partials/actions.html
mkdocs_fedi_comments/overrides/partials/comments.html
mkdocs_fedi_comments-0.1.7.dist-info/METADATA
mkdocs_fedi_comments-0.1.7.dist-info/WHEEL
mkdocs_fedi_comments-0.1.7.dist-info/entry_points.txt
mkdocs_fedi_comments-0.1.7.dist-info/RECORD
