Metadata-Version: 2.4
Name: mkdocs-fedi-comments
Version: 0.1.7
Summary: Plugin enables adding comments to mkdocs sites from the Fediverse through an external service
Requires-Python: >=3.11
Requires-Dist: mkdocs>=1.6.1
